ubersmith_client/__init__.py
ubersmith_client/_http_utils.py
ubersmith_client/api.py
ubersmith_client/exceptions.py
ubersmith_client/ubersmith_api.py
ubersmith_client/ubersmith_request.py
ubersmith_client/ubersmith_request_get.py
ubersmith_client/ubersmith_request_post.py
python_ubersmithclient-2.0.9.dist-info/AUTHORS
python_ubersmithclient-2.0.9.dist-info/LICENSE
python_ubersmithclient-2.0.9.dist-info/METADATA
python_ubersmithclient-2.0.9.dist-info/WHEEL
python_ubersmithclient-2.0.9.dist-info/pbr.json
python_ubersmithclient-2.0.9.dist-info/top_level.txt
python_ubersmithclient-2.0.9.dist-info/RECORD
