Metadata-Version: 2.1
Name: python-ubersmithclient
Version: 2.0.9
Summary: Another ubersmith lib
Home-page: https://github.com/internap/python-ubersmithclient
Author: Internap
Author-email: opensource@internap.com
License: UNKNOWN
Platform: UNKNOWN
Classifier: Development Status :: 5 - Production/Stable
Classifier: Intended Audience :: Developers
Classifier: License :: OSI Approved :: Apache Software License
Classifier: Operating System :: POSIX
Classifier: Programming Language :: Python :: 2.7
Classifier: Programming Language :: Python :: 3.4
Classifier: Programming Language :: Python :: 3.5
Classifier: Programming Language :: Python :: 3.6
Classifier: Programming Language :: Python :: 3.7
Classifier: Programming Language :: Python :: 3.8
License-File: LICENSE
License-File: AUTHORS
Requires-Dist: requests (==2.21.0) ; (python_version<'3.6')
Requires-Dist: requests ; (python_version>='3.6')
